{
  "plan_id": "c6859972-70bd-4c65-8091-89d848548698",
  "created_at": "2026-01-04T03:01:57.853451+00:00",
  "summary": "在公共花园铺设 GM4 Lively Lily Pads，把睡莲改造成彩灯展示，执行 gm4_lively_lily_pads:init。",
  "status": "completed",
  "steps": [
    {
      "step_id": "fallback-1",
      "title": "阶段 1",
      "description": "目标：在公共花园铺设 GM4 Lively Lily Pads，把睡莲改造成彩灯展示，执行 gm4_lively_lily_pads:init",
      "target_region": null,
      "required_mod": null,
      "dependencies": []
    },
    {
      "step_id": "fallback-2",
      "title": "阶段 2",
      "description": "执行：围绕目标拆解两步执行：准备资源并落地社区验证。",
      "target_region": null,
      "required_mod": null,
      "dependencies": []
    }
  ],
  "resource_ledger": {},
  "risk_notes": [],
  "mod_hooks": [
    "gm4:lively_lily_pads"
  ],
  "origin_scenario": "default"
}